LICENSE
MANIFEST.in
README.md
setup.py
sofa-spm.py
sofa_spm.egg-info/PKG-INFO
sofa_spm.egg-info/SOURCES.txt
sofa_spm.egg-info/dependency_links.txt
sofa_spm.egg-info/requires.txt
sofa_spm.egg-info/top_level.txt
sofa_spm.egg-info/zip-safe
spm/__init__.py
spm/getcomponents.py
spm/repo.py
spm/recipes/Consortium/HighOrder.sp
spm/recipes/Consortium/SofaQtQuick.sp
spm/recipes/Defrost/BeamAdapter.sp
spm/recipes/Defrost/DefrostAllPlugins.sp
spm/recipes/Defrost/ModelOrderReduction.sp
spm/recipes/Defrost/STLIB.sp
spm/recipes/Defrost/SoftRobots.Inverse.sp
spm/recipes/Defrost/SoftRobots.sp
spm/recipes/Defrost/sofa-shells.sp
spm/recipes/Defrost/Robots/Echelon3.sp
spm/recipes/Defrost/Robots/SOFIA.sp